nose_specs.py
pspecs.py
pytest_specs.py
setup.py
pspecs.egg-info/PKG-INFO
pspecs.egg-info/SOURCES.txt
pspecs.egg-info/dependency_links.txt
pspecs.egg-info/entry_points.txt
pspecs.egg-info/requires.txt
pspecs.egg-info/top_level.txt